LICENSE.md
README.md
setup.py
BiomationScripter/__init__.py
BiomationScripter.egg-info/PKG-INFO
BiomationScripter.egg-info/SOURCES.txt
BiomationScripter.egg-info/dependency_links.txt
BiomationScripter.egg-info/top_level.txt
BiomationScripter/EchoProto/__init__.py
BiomationScripter/EchoProto/Templates/Colour_Mixing.py
BiomationScripter/EchoProto/Templates/Loop_Assembly.py
BiomationScripter/EchoProto/Templates/NEBridge_Loop_Assembly.py
BiomationScripter/EchoProto/Templates/PCR.py
BiomationScripter/EchoProto/Templates/__init__.py
BiomationScripter/OTProto/__init__.py
BiomationScripter/OTProto/Templates/DNA_fmol_Dilution.py
BiomationScripter/OTProto/Templates/Design_Of_Experiments.py
BiomationScripter/OTProto/Templates/Heat_Shock_Transformation.py
BiomationScripter/OTProto/Templates/Primer_Mixing.py
BiomationScripter/OTProto/Templates/Protocol_From_Layouts.py
BiomationScripter/OTProto/Templates/Spot_Plating.py
BiomationScripter/OTProto/Templates/Standard_iGEM_Calibration.py
BiomationScripter/OTProto/Templates/__init__.py