Metadata-Version: 2.1
Name: BiomationScripter
Version: 0.2.2
Summary: Tools for scripting bio-automation protocols
Author: Bradley Brown
Author-email: bradley.brown4@hotmail.co.uk
License-File: LICENSE.md
